Metadata-Version: 2.1
Name: cvlab-medical
Version: 0.1
Summary: # Medical toolkit for CV-Lab
Home-page: https://github.com/cvlab-ai/cvlab_medical
Author: Adam Brzeski, Jan Cychnerski
Author-email: adam.m.brzeski@gmail.com, jan.cychnerski@gmail.com
License: AGPL-3.0+
Platform: UNKNOWN
Requires-Python: >=3.3
